LICENSE
MANIFEST.in
README.rst
requirements-docs.txt
requirements-tests.txt
requirements.txt
setup.py
contacts/__init__.py
contacts/admin.py
contacts/forms.py
contacts/managers.py
contacts/models.py
contacts/urls.py
contacts/migrations/0001_initial.py
contacts/migrations/__init__.py
contacts/templates/base.html
contacts/templates/admin/contacts/company/change_form.html
contacts/templates/admin/contacts/person/change_form.html
contacts/templates/contacts/_comment_list.html
contacts/templates/contacts/_email_address_form.html
contacts/templates/contacts/_email_address_list.html
contacts/templates/contacts/_instant_messenger_form.html
contacts/templates/contacts/_instant_messenger_list.html
contacts/templates/contacts/_phone_number_form.html
contacts/templates/contacts/_phone_number_list.html
contacts/templates/contacts/_special_date_form.html
contacts/templates/contacts/_special_date_list.html
contacts/templates/contacts/_street_address_form.html
contacts/templates/contacts/_street_address_list.html
contacts/templates/contacts/_web_site_form.html
contacts/templates/contacts/_web_site_list.html
contacts/templates/contacts/base.html
contacts/templates/contacts/company/base.html
contacts/templates/contacts/company/create.html
contacts/templates/contacts/company/delete.html
contacts/templates/contacts/company/detail.html
contacts/templates/contacts/company/list.html
contacts/templates/contacts/company/update.html
contacts/templates/contacts/group/base.html
contacts/templates/contacts/group/create.html
contacts/templates/contacts/group/delete.html
contacts/templates/contacts/group/detail.html
contacts/templates/contacts/group/list.html
contacts/templates/contacts/group/update.html
contacts/templates/contacts/person/base.html
contacts/templates/contacts/person/create.html
contacts/templates/contacts/person/delete.html
contacts/templates/contacts/person/detail.html
contacts/templates/contacts/person/list.html
contacts/templates/contacts/person/update.html
django_contacts.egg-info/PKG-INFO
django_contacts.egg-info/SOURCES.txt
django_contacts.egg-info/dependency_links.txt
django_contacts.egg-info/requires.txt
django_contacts.egg-info/top_level.txt