Metadata-Version: 1.1
Name: django-contacts
Version: 0.6.0
Summary: A Django address book application.
Home-page: http://github.com/myles/django-contacts
Author: Myles Braithwaite
Author-email: me@mylesbraithwaite.com
License: BSD License
Platform: UNKNOWN
Classifier: Development Status :: 4 - Beta
Classifier: Environment :: Web Environment
Classifier: Framework :: Django
Classifier: Intended Audience :: Developers
Classifier: License :: OSI Approved :: BSD License
Classifier: Operating System :: OS Independent
Classifier: Programming Language :: Python
Classifier: Topic :: Internet :: WWW/HTTP
